s3cookiejar.py
s3cookiejar-1.0.0.dist-info/DESCRIPTION.rst
s3cookiejar-1.0.0.dist-info/METADATA
s3cookiejar-1.0.0.dist-info/RECORD
s3cookiejar-1.0.0.dist-info/WHEEL
s3cookiejar-1.0.0.dist-info/metadata.json
s3cookiejar-1.0.0.dist-info/top_level.txt
