Metadata-Version: 2.0
Name: s3cookiejar
Version: 1.0.0
Summary: HTTP Cookie Jar that reads from/writes to an S3 bucket (optional KMS encryption)
Home-page: https://github.com/hurricanelabs/python-s3cookiejar
Author: Steve McMaster
Author-email: mcmaster@hurricanelabs.com
License: MIT License
Keywords: aws,s3,cookiejar,requests
Platform: UNKNOWN
Classifier: License :: OSI Approved :: MIT License
Classifier: Programming Language :: Python
Classifier: Development Status :: 4 - Beta
Requires-Dist: boto3
Requires-Dist: six
